[
  {
    "title": "big ass"
  },
  {
    "title": "big breasts"
  },
  {
    "title": "hand job"
  },
  {
    "title": "doggy style"
  },
  {
    "title": "emo"
  },
  {
    "title": "teen"
  },
  {
    "title": "only fans"
  },
  {
    "title": "toy"
  },
  {
    "title": "blonde"
  },
  {
    "title": "drop breasts"
  },
  {
    "title": "asian"
  },
  {
    "title": "blowjob"
  },
  {
    "title": "red head"
  },
  {
    "title": "ebony"
  },
  {
    "title": "roleplay"
  },
  {
    "title": "face baby"
  },
  {
    "title": "glasses"
  },
  {
    "title": "public"
  },
  {
    "title": "long air"
  },
  {
    "title": "riding"
  },
  {
    "title": "gym"
  },
  {
    "title": "cosplay"
  },
  {
    "title": "squirt"
  },
  {
    "title": "small breasts"
  },
  {
    "title": "argentina"
  },
  {
    "title": "ai"
  },
  {
    "title": "privady"
  },
  {
    "title": "anal"
  },
  {
    "title": "boob job"
  },
  {
    "title": "e girl"
  },
  {
    "title": "solo"
  },
  {
    "title": "foot job"
  },
  {
    "title": "curvy"
  },
  {
    "title": "skinny"
  },
  {
    "title": "amateur"
  },
  {
    "title": "natural"
  }
]